{"compressed":"gzip-tab-files-v1","version":"2026-07-23T13:28:40.088Z","_meta":{"source":"OpenStreetMap via Geofabrik","sourceUrl":"https://download.geofabrik.de/europe/latvia-latest.osm.pbf","license":"ODbL 1.0","licenseUrl":"https://www.openstreetmap.org/copyright","country":"LV","generatedAt":"2026-07-23T13:28:40.088Z","coordinateMethod":"point coordinates; bounding-box center for ways and relations"},"parts":{"camps":{"file":"map-data/lotyssko/camps.json.gz","bytes":16223,"sourceBytes":103049,"count":310,"fetchedAt":1784813320088},"sights":{"file":"map-data/lotyssko/sights.json.gz","bytes":175663,"sourceBytes":1473740,"count":5904,"fetchedAt":1784813320088},"nature":{"file":"map-data/lotyssko/nature.json.gz","bytes":60006,"sourceBytes":602197,"count":2399,"fetchedAt":1784813320088},"food":{"file":"map-data/lotyssko/food.json.gz","bytes":346377,"sourceBytes":4188268,"count":16905,"fetchedAt":1784813320088},"services":{"file":"map-data/lotyssko/services.json.gz","bytes":184674,"sourceBytes":1553020,"count":6027,"fetchedAt":1784813320088},"spa":{"file":"map-data/lotyssko/spa.json.gz","bytes":972,"sourceBytes":4004,"count":15,"fetchedAt":1784813320088},"lodging":{"file":"map-data/lotyssko/lodging.json.gz","bytes":43955,"sourceBytes":281803,"count":1061,"fetchedAt":1784813320088},"zones":{"file":"map-data/lotyssko/zones.json.gz","bytes":13682,"sourceBytes":68527,"count":184,"fetchedAt":1784813320088}}}